odoo/addons/auth_admin_passkey_totp_mail_enforce/README.rst
odoo/addons/auth_admin_passkey_totp_mail_enforce/__init__.py
odoo/addons/auth_admin_passkey_totp_mail_enforce/__manifest__.py
odoo/addons/auth_admin_passkey_totp_mail_enforce/i18n/auth_admin_passkey_totp_mail_enforce.pot
odoo/addons/auth_admin_passkey_totp_mail_enforce/i18n/it.po
odoo/addons/auth_admin_passkey_totp_mail_enforce/models/__init__.py
odoo/addons/auth_admin_passkey_totp_mail_enforce/models/res_users.py
odoo/addons/auth_admin_passkey_totp_mail_enforce/readme/CONTRIBUTORS.md
odoo/addons/auth_admin_passkey_totp_mail_enforce/readme/DESCRIPTION.md
odoo/addons/auth_admin_passkey_totp_mail_enforce/static/description/icon.png
odoo/addons/auth_admin_passkey_totp_mail_enforce/static/description/index.html
odoo/addons/auth_admin_passkey_totp_mail_enforce/tests/__init__.py
odoo/addons/auth_admin_passkey_totp_mail_enforce/tests/test_login.py
odoo_addon_auth_admin_passkey_totp_mail_enforce-17.0.1.0.0.4.dist-info/METADATA
odoo_addon_auth_admin_passkey_totp_mail_enforce-17.0.1.0.0.4.dist-info/WHEEL
odoo_addon_auth_admin_passkey_totp_mail_enforce-17.0.1.0.0.4.dist-info/top_level.txt
odoo_addon_auth_admin_passkey_totp_mail_enforce-17.0.1.0.0.4.dist-info/RECORD
